{
  "passed": [
    "Node.js version check",
    "Version consistency",
    "Full test suite",
    "License compliance check",
    "Secret scanner",
    "Performance tests",
    "Correct branch"
  ],
  "failed": [],
  "warnings": [
    "NPM security audit",
    "Uncommitted changes present"
  ],
  "testResults": {},
  "versionInfo": {
    "package": "7.1.1",
    "versionFile": "7.1.1",
    "readme": "7.1.1",
    "buildDate": "2025-07-29",
    "description": "Enhanced RSU input with stock symbol selection and real-time price lookup"
  },
  "timestamp": "2025-07-29T14:51:29.466Z",
  "summary": {
    "ready": true,
    "passedChecks": 7,
    "failedChecks": 0,
    "warnings": 2
  }
}